hsoft/__init__.py
hsoft/hobj1.py
hsoft-0.0.2.dist-info/METADATA
hsoft-0.0.2.dist-info/WHEEL
hsoft-0.0.2.dist-info/top_level.txt
hsoft-0.0.2.dist-info/RECORD
