Metadata-Version: 2.1
Name: hsoft
Version: 0.0.2
Summary: My package description
Requires-Python: >=3.6
